{
    "XLB": {
        "name": "Materials",
        "x": 99.376,
        "y": 102.5402,
        "rsr": 99.376,
        "rsm": 102.5402,
        "relative_strength": 0.6781,
        "quadrant": "Improving (개선)",
        "date": "2026-05-27",
        "calculation_method": "rrg_blog.py"
    },
    "XLC": {
        "name": "Communication Services",
        "x": 98.0887,
        "y": 99.7919,
        "rsr": 98.0887,
        "rsm": 99.7919,
        "relative_strength": 1.5367,
        "quadrant": "Lagging (지연)",
        "date": "2026-05-27",
        "calculation_method": "rrg_blog.py"
    },
    "XLE": {
        "name": "Energy",
        "x": 99.2378,
        "y": 100.6551,
        "rsr": 99.2378,
        "rsm": 100.6551,
        "relative_strength": 0.7694,
        "quadrant": "Improving (개선)",
        "date": "2026-05-27",
        "calculation_method": "rrg_blog.py"
    },
    "XLF": {
        "name": "Financials",
        "x": 99.2545,
        "y": 101.4979,
        "rsr": 99.2545,
        "rsm": 101.4979,
        "relative_strength": 0.6896,
        "quadrant": "Improving (개선)",
        "date": "2026-05-27",
        "calculation_method": "rrg_blog.py"
    },
    "XLI": {
        "name": "Industrials",
        "x": 99.6563,
        "y": 102.9386,
        "rsr": 99.6563,
        "rsm": 102.9386,
        "relative_strength": 2.3181,
        "quadrant": "Improving (개선)",
        "date": "2026-05-27",
        "calculation_method": "rrg_blog.py"
    },
    "XLK": {
        "name": "Technology",
        "x": 102.2718,
        "y": 102.2721,
        "rsr": 102.2718,
        "rsm": 102.2721,
        "relative_strength": 2.4623,
        "quadrant": "Leading (선도)",
        "date": "2026-05-27",
        "calculation_method": "rrg_blog.py"
    },
    "XLP": {
        "name": "Consumer Staples",
        "x": 97.9086,
        "y": 99.8975,
        "rsr": 97.9086,
        "rsm": 99.8975,
        "relative_strength": 1.1122,
        "quadrant": "Lagging (지연)",
        "date": "2026-05-27",
        "calculation_method": "rrg_blog.py"
    },
    "XLU": {
        "name": "Utilities",
        "x": 99.8141,
        "y": 102.4035,
        "rsr": 99.8141,
        "rsm": 102.4035,
        "relative_strength": 0.6029,
        "quadrant": "Improving (개선)",
        "date": "2026-05-27",
        "calculation_method": "rrg_blog.py"
    },
    "XLV": {
        "name": "Healthcare",
        "x": 100.2078,
        "y": 101.6646,
        "rsr": 100.2078,
        "rsm": 101.6646,
        "relative_strength": 1.9751,
        "quadrant": "Leading (선도)",
        "date": "2026-05-27",
        "calculation_method": "rrg_blog.py"
    },
    "XLY": {
        "name": "Consumer Discretionary",
        "x": 99.6416,
        "y": 102.3319,
        "rsr": 99.6416,
        "rsm": 102.3319,
        "relative_strength": 1.5886,
        "quadrant": "Improving (개선)",
        "date": "2026-05-27",
        "calculation_method": "rrg_blog.py"
    },
    "XLRE": {
        "name": "Real Estate",
        "x": 99.6807,
        "y": 102.0902,
        "rsr": 99.6807,
        "rsm": 102.0902,
        "relative_strength": 0.5946,
        "quadrant": "Improving (개선)",
        "date": "2026-05-27",
        "calculation_method": "rrg_blog.py"
    }
}